{"nodes": [{"id": "c_blade_addons_new_blade_addons_new_src_main_java_blade_addon_fishmodinit_java", "label": "FishModInit.java", "file_type": "code", "source_file": "C:\\blade-addons-new\\blade-addons-new\\src\\main\\java\\blade\\addon\\FishModInit.java", "source_location": "L1"}, {"id": "addon_fishmodinit_fishmodinit", "label": "FishModInit", "file_type": "code", "source_file": "C:\\blade-addons-new\\blade-addons-new\\src\\main\\java\\blade\\addon\\FishModInit.java", "source_location": "L47"}, {"id": "modinitializer", "label": "ModInitializer", "file_type": "code", "source_file": "", "source_location": ""}, {"id": "addon_fishmodinit_fishmodinit_oninitialize", "label": ".onInitialize()", "file_type": "code", "source_file": "C:\\blade-addons-new\\blade-addons-new\\src\\main\\java\\blade\\addon\\FishModInit.java", "source_location": "L48"}], "edges": [{"source": "c_blade_addons_new_blade_addons_new_src_main_java_blade_addon_fishmodinit_java", "target": "bossbarfeature", "relation": "imports", "context": "import", "confidence": "EXTRACTED", "source_file": "C:\\blade-addons-new\\blade-addons-new\\src\\main\\java\\blade\\addon\\FishModInit.java", "source_location": "L3", "weight": 1.0}, {"source": "c_blade_addons_new_blade_addons_new_src_main_java_blade_addon_fishmodinit_java", "target": "wikiscreen", "relation": "imports", "context": "import", "confidence": "EXTRACTED", "source_file": "C:\\blade-addons-new\\blade-addons-new\\src\\main\\java\\blade\\addon\\FishModInit.java", "source_location": "L4", "weight": 1.0}, {"source": "c_blade_addons_new_blade_addons_new_src_main_java_blade_addon_fishmodinit_java", "target": "bridgebot", "relation": "imports", "context": "import", "confidence": "EXTRACTED", "source_file": "C:\\blade-addons-new\\blade-addons-new\\src\\main\\java\\blade\\addon\\FishModInit.java", "source_location": "L5", "weight": 1.0}, {"source": "c_blade_addons_new_blade_addons_new_src_main_java_blade_addon_fishmodinit_java", "target": "fishhudeditor", "relation": "imports", "context": "import", "confidence": "EXTRACTED", "source_file": "C:\\blade-addons-new\\blade-addons-new\\src\\main\\java\\blade\\addon\\FishModInit.java", "source_location": "L6", "weight": 1.0}, {"source": "c_blade_addons_new_blade_addons_new_src_main_java_blade_addon_fishmodinit_java", "target": "powdertracker", "relation": "imports", "context": "import", "confidence": "EXTRACTED", "source_file": "C:\\blade-addons-new\\blade-addons-new\\src\\main\\java\\blade\\addon\\FishModInit.java", "source_location": "L7", "weight": 1.0}, {"source": "c_blade_addons_new_blade_addons_new_src_main_java_blade_addon_fishmodinit_java", "target": "slayerxptracker", "relation": "imports", "context": "import", "confidence": "EXTRACTED", "source_file": "C:\\blade-addons-new\\blade-addons-new\\src\\main\\java\\blade\\addon\\FishModInit.java", "source_location": "L8", "weight": 1.0}, {"source": "c_blade_addons_new_blade_addons_new_src_main_java_blade_addon_fishmodinit_java", "target": "soulflowhud", "relation": "imports", "context": "import", "confidence": "EXTRACTED", "source_file": "C:\\blade-addons-new\\blade-addons-new\\src\\main\\java\\blade\\addon\\FishModInit.java", "source_location": "L9", "weight": 1.0}, {"source": "c_blade_addons_new_blade_addons_new_src_main_java_blade_addon_fishmodinit_java", "target": "warpmapfeature", "relation": "imports", "context": "import", "confidence": "EXTRACTED", "source_file": "C:\\blade-addons-new\\blade-addons-new\\src\\main\\java\\blade\\addon\\FishModInit.java", "source_location": "L10", "weight": 1.0}, {"source": "c_blade_addons_new_blade_addons_new_src_main_java_blade_addon_fishmodinit_java", "target": "folderutility", "relation": "imports", "context": "import", "confidence": "EXTRACTED", "source_file": "C:\\blade-addons-new\\blade-addons-new\\src\\main\\java\\blade\\addon\\FishModInit.java", "source_location": "L11", "weight": 1.0}, {"source": "c_blade_addons_new_blade_addons_new_src_main_java_blade_addon_fishmodinit_java", "target": "config", "relation": "imports", "context": "import", "confidence": "EXTRACTED", "source_file": "C:\\blade-addons-new\\blade-addons-new\\src\\main\\java\\blade\\addon\\FishModInit.java", "source_location": "L12", "weight": 1.0}, {"source": "c_blade_addons_new_blade_addons_new_src_main_java_blade_addon_fishmodinit_java", "target": "keybinds", "relation": "imports", "context": "import", "confidence": "EXTRACTED", "source_file": "C:\\blade-addons-new\\blade-addons-new\\src\\main\\java\\blade\\addon\\FishModInit.java", "source_location": "L13", "weight": 1.0}, {"source": "c_blade_addons_new_blade_addons_new_src_main_java_blade_addon_fishmodinit_java", "target": "customevents", "relation": "imports", "context": "import", "confidence": "EXTRACTED", "source_file": "C:\\blade-addons-new\\blade-addons-new\\src\\main\\java\\blade\\addon\\FishModInit.java", "source_location": "L14", "weight": 1.0}, {"source": "c_blade_addons_new_blade_addons_new_src_main_java_blade_addon_fishmodinit_java", "target": "debug", "relation": "imports", "context": "import", "confidence": "EXTRACTED", "source_file": "C:\\blade-addons-new\\blade-addons-new\\src\\main\\java\\blade\\addon\\FishModInit.java", "source_location": "L15", "weight": 1.0}, {"source": "c_blade_addons_new_blade_addons_new_src_main_java_blade_addon_fishmodinit_java", "target": "location", "relation": "imports", "context": "import", "confidence": "EXTRACTED", "source_file": "C:\\blade-addons-new\\blade-addons-new\\src\\main\\java\\blade\\addon\\FishModInit.java", "source_location": "L16", "weight": 1.0}, {"source": "c_blade_addons_new_blade_addons_new_src_main_java_blade_addon_fishmodinit_java", "target": "mayorapi", "relation": "imports", "context": "import", "confidence": "EXTRACTED", "source_file": "C:\\blade-addons-new\\blade-addons-new\\src\\main\\java\\blade\\addon\\FishModInit.java", "source_location": "L17", "weight": 1.0}, {"source": "c_blade_addons_new_blade_addons_new_src_main_java_blade_addon_fishmodinit_java", "target": "scheduler", "relation": "imports", "context": "import", "confidence": "EXTRACTED", "source_file": "C:\\blade-addons-new\\blade-addons-new\\src\\main\\java\\blade\\addon\\FishModInit.java", "source_location": "L18", "weight": 1.0}, {"source": "c_blade_addons_new_blade_addons_new_src_main_java_blade_addon_fishmodinit_java", "target": "dungeondeathmessage", "relation": "imports", "context": "import", "confidence": "EXTRACTED", "source_file": "C:\\blade-addons-new\\blade-addons-new\\src\\main\\java\\blade\\addon\\FishModInit.java", "source_location": "L19", "weight": 1.0}, {"source": "c_blade_addons_new_blade_addons_new_src_main_java_blade_addon_fishmodinit_java", "target": "partycommandhandler", "relation": "imports", "context": "import", "confidence": "EXTRACTED", "source_file": "C:\\blade-addons-new\\blade-addons-new\\src\\main\\java\\blade\\addon\\FishModInit.java", "source_location": "L20", "weight": 1.0}, {"source": "c_blade_addons_new_blade_addons_new_src_main_java_blade_addon_fishmodinit_java", "target": "fishesttotal", "relation": "imports", "context": "import", "confidence": "EXTRACTED", "source_file": "C:\\blade-addons-new\\blade-addons-new\\src\\main\\java\\blade\\addon\\FishModInit.java", "source_location": "L21", "weight": 1.0}, {"source": "c_blade_addons_new_blade_addons_new_src_main_java_blade_addon_fishmodinit_java", "target": "fishpuzzledisplay", "relation": "imports", "context": "import", "confidence": "EXTRACTED", "source_file": "C:\\blade-addons-new\\blade-addons-new\\src\\main\\java\\blade\\addon\\FishModInit.java", "source_location": "L22", "weight": 1.0}, {"source": "c_blade_addons_new_blade_addons_new_src_main_java_blade_addon_fishmodinit_java", "target": "lagtracker", "relation": "imports", "context": "import", "confidence": "EXTRACTED", "source_file": "C:\\blade-addons-new\\blade-addons-new\\src\\main\\java\\blade\\addon\\FishModInit.java", "source_location": "L23", "weight": 1.0}, {"source": "c_blade_addons_new_blade_addons_new_src_main_java_blade_addon_fishmodinit_java", "target": "fishpartytracker", "relation": "imports", "context": "import", "confidence": "EXTRACTED", "source_file": "C:\\blade-addons-new\\blade-addons-new\\src\\main\\java\\blade\\addon\\FishModInit.java", "source_location": "L24", "weight": 1.0}, {"source": "c_blade_addons_new_blade_addons_new_src_main_java_blade_addon_fishmodinit_java", "target": "puzzledisplay", "relation": "imports", "context": "import", "confidence": "EXTRACTED", "source_file": "C:\\blade-addons-new\\blade-addons-new\\src\\main\\java\\blade\\addon\\FishModInit.java", "source_location": "L25", "weight": 1.0}, {"source": "c_blade_addons_new_blade_addons_new_src_main_java_blade_addon_fishmodinit_java", "target": "components", "relation": "imports", "context": "import", "confidence": "EXTRACTED", "source_file": "C:\\blade-addons-new\\blade-addons-new\\src\\main\\java\\blade\\addon\\FishModInit.java", "source_location": "L26", "weight": 1.0}, {"source": "c_blade_addons_new_blade_addons_new_src_main_java_blade_addon_fishmodinit_java", "target": "entityutil", "relation": "imports", "context": "import", "confidence": "EXTRACTED", "source_file": "C:\\blade-addons-new\\blade-addons-new\\src\\main\\java\\blade\\addon\\FishModInit.java", "source_location": "L27", "weight": 1.0}, {"source": "c_blade_addons_new_blade_addons_new_src_main_java_blade_addon_fishmodinit_java", "target": "partyutil", "relation": "imports", "context": "import", "confidence": "EXTRACTED", "source_file": "C:\\blade-addons-new\\blade-addons-new\\src\\main\\java\\blade\\addon\\FishModInit.java", "source_location": "L28", "weight": 1.0}, {"source": "c_blade_addons_new_blade_addons_new_src_main_java_blade_addon_fishmodinit_java", "target": "phase", "relation": "imports", "context": "import", "confidence": "EXTRACTED", "source_file": "C:\\blade-addons-new\\blade-addons-new\\src\\main\\java\\blade\\addon\\FishModInit.java", "source_location": "L29", "weight": 1.0}, {"source": "c_blade_addons_new_blade_addons_new_src_main_java_blade_addon_fishmodinit_java", "target": "section", "relation": "imports", "context": "import", "confidence": "EXTRACTED", "source_file": "C:\\blade-addons-new\\blade-addons-new\\src\\main\\java\\blade\\addon\\FishModInit.java", "source_location": "L30", "weight": 1.0}, {"source": "c_blade_addons_new_blade_addons_new_src_main_java_blade_addon_fishmodinit_java", "target": "renderingevents", "relation": "imports", "context": "import", "confidence": "EXTRACTED", "source_file": "C:\\blade-addons-new\\blade-addons-new\\src\\main\\java\\blade\\addon\\FishModInit.java", "source_location": "L31", "weight": 1.0}, {"source": "c_blade_addons_new_blade_addons_new_src_main_java_blade_addon_fishmodinit_java", "target": "fishmodscreen", "relation": "imports", "context": "import", "confidence": "EXTRACTED", "source_file": "C:\\blade-addons-new\\blade-addons-new\\src\\main\\java\\blade\\addon\\FishModInit.java", "source_location": "L32", "weight": 1.0}, {"source": "c_blade_addons_new_blade_addons_new_src_main_java_blade_addon_fishmodinit_java", "target": "constants", "relation": "imports", "context": "import", "confidence": "EXTRACTED", "source_file": "C:\\blade-addons-new\\blade-addons-new\\src\\main\\java\\blade\\addon\\FishModInit.java", "source_location": "L33", "weight": 1.0}, {"source": "c_blade_addons_new_blade_addons_new_src_main_java_blade_addon_fishmodinit_java", "target": "misc", "relation": "imports", "context": "import", "confidence": "EXTRACTED", "source_file": "C:\\blade-addons-new\\blade-addons-new\\src\\main\\java\\blade\\addon\\FishModInit.java", "source_location": "L34", "weight": 1.0}, {"source": "c_blade_addons_new_blade_addons_new_src_main_java_blade_addon_fishmodinit_java", "target": "fishconfig", "relation": "imports", "context": "import", "confidence": "EXTRACTED", "source_file": "C:\\blade-addons-new\\blade-addons-new\\src\\main\\java\\blade\\addon\\FishModInit.java", "source_location": "L35", "weight": 1.0}, {"source": "c_blade_addons_new_blade_addons_new_src_main_java_blade_addon_fishmodinit_java", "target": "modinitializer", "relation": "imports", "context": "import", "confidence": "EXTRACTED", "source_file": "C:\\blade-addons-new\\blade-addons-new\\src\\main\\java\\blade\\addon\\FishModInit.java", "source_location": "L36", "weight": 1.0}, {"source": "c_blade_addons_new_blade_addons_new_src_main_java_blade_addon_fishmodinit_java", "target": "stringargumenttype", "relation": "imports", "context": "import", "confidence": "EXTRACTED", "source_file": "C:\\blade-addons-new\\blade-addons-new\\src\\main\\java\\blade\\addon\\FishModInit.java", "source_location": "L37", "weight": 1.0}, {"source": "c_blade_addons_new_blade_addons_new_src_main_java_blade_addon_fishmodinit_java", "target": "clientcommandmanager", "relation": "imports", "context": "import", "confidence": "EXTRACTED", "source_file": "C:\\blade-addons-new\\blade-addons-new\\src\\main\\java\\blade\\addon\\FishModInit.java", "source_location": "L38", "weight": 1.0}, {"source": "c_blade_addons_new_blade_addons_new_src_main_java_blade_addon_fishmodinit_java", "target": "clientcommandregistrationcallback", "relation": "imports", "context": "import", "confidence": "EXTRACTED", "source_file": "C:\\blade-addons-new\\blade-addons-new\\src\\main\\java\\blade\\addon\\FishModInit.java", "source_location": "L39", "weight": 1.0}, {"source": "c_blade_addons_new_blade_addons_new_src_main_java_blade_addon_fishmodinit_java", "target": "hudrendercallback", "relation": "imports", "context": "import", "confidence": "EXTRACTED", "source_file": "C:\\blade-addons-new\\blade-addons-new\\src\\main\\java\\blade\\addon\\FishModInit.java", "source_location": "L40", "weight": 1.0}, {"source": "c_blade_addons_new_blade_addons_new_src_main_java_blade_addon_fishmodinit_java", "target": "fabricloader", "relation": "imports", "context": "import", "confidence": "EXTRACTED", "source_file": "C:\\blade-addons-new\\blade-addons-new\\src\\main\\java\\blade\\addon\\FishModInit.java", "source_location": "L41", "weight": 1.0}, {"source": "c_blade_addons_new_blade_addons_new_src_main_java_blade_addon_fishmodinit_java", "target": "minecraftclient", "relation": "imports", "context": "import", "confidence": "EXTRACTED", "source_file": "C:\\blade-addons-new\\blade-addons-new\\src\\main\\java\\blade\\addon\\FishModInit.java", "source_location": "L42", "weight": 1.0}, {"source": "c_blade_addons_new_blade_addons_new_src_main_java_blade_addon_fishmodinit_java", "target": "clientplaynetworkhandler", "relation": "imports", "context": "import", "confidence": "EXTRACTED", "source_file": "C:\\blade-addons-new\\blade-addons-new\\src\\main\\java\\blade\\addon\\FishModInit.java", "source_location": "L43", "weight": 1.0}, {"source": "c_blade_addons_new_blade_addons_new_src_main_java_blade_addon_fishmodinit_java", "target": "playerlistentry", "relation": "imports", "context": "import", "confidence": "EXTRACTED", "source_file": "C:\\blade-addons-new\\blade-addons-new\\src\\main\\java\\blade\\addon\\FishModInit.java", "source_location": "L44", "weight": 1.0}, {"source": "c_blade_addons_new_blade_addons_new_src_main_java_blade_addon_fishmodinit_java", "target": "text", "relation": "imports", "context": "import", "confidence": "EXTRACTED", "source_file": "C:\\blade-addons-new\\blade-addons-new\\src\\main\\java\\blade\\addon\\FishModInit.java", "source_location": "L45", "weight": 1.0}, {"source": "c_blade_addons_new_blade_addons_new_src_main_java_blade_addon_fishmodinit_java", "target": "addon_fishmodinit_fishmodinit", "relation": "contains", "confidence": "EXTRACTED", "source_file": "C:\\blade-addons-new\\blade-addons-new\\src\\main\\java\\blade\\addon\\FishModInit.java", "source_location": "L47", "weight": 1.0}, {"source": "addon_fishmodinit_fishmodinit", "target": "modinitializer", "relation": "implements", "confidence": "EXTRACTED", "source_file": "C:\\blade-addons-new\\blade-addons-new\\src\\main\\java\\blade\\addon\\FishModInit.java", "source_location": "L47", "weight": 1.0}, {"source": "addon_fishmodinit_fishmodinit", "target": "addon_fishmodinit_fishmodinit_oninitialize", "relation": "method", "confidence": "EXTRACTED", "source_file": "C:\\blade-addons-new\\blade-addons-new\\src\\main\\java\\blade\\addon\\FishModInit.java", "source_location": "L48", "weight": 1.0}], "raw_calls": [{"caller_nid": "addon_fishmodinit_fishmodinit_oninitialize", "callee": "load", "is_member_call": false, "source_file": "C:\\blade-addons-new\\blade-addons-new\\src\\main\\java\\blade\\addon\\FishModInit.java", "source_location": "L51"}, {"caller_nid": "addon_fishmodinit_fishmodinit_oninitialize", "callee": "init", "is_member_call": false, "source_file": "C:\\blade-addons-new\\blade-addons-new\\src\\main\\java\\blade\\addon\\FishModInit.java", "source_location": "L54"}, {"caller_nid": "addon_fishmodinit_fishmodinit_oninitialize", "callee": "init", "is_member_call": false, "source_file": "C:\\blade-addons-new\\blade-addons-new\\src\\main\\java\\blade\\addon\\FishModInit.java", "source_location": "L55"}, {"caller_nid": "addon_fishmodinit_fishmodinit_oninitialize", "callee": "init", "is_member_call": false, "source_file": "C:\\blade-addons-new\\blade-addons-new\\src\\main\\java\\blade\\addon\\FishModInit.java", "source_location": "L56"}, {"caller_nid": "addon_fishmodinit_fishmodinit_oninitialize", "callee": "init", "is_member_call": false, "source_file": "C:\\blade-addons-new\\blade-addons-new\\src\\main\\java\\blade\\addon\\FishModInit.java", "source_location": "L57"}, {"caller_nid": "addon_fishmodinit_fishmodinit_oninitialize", "callee": "init", "is_member_call": false, "source_file": "C:\\blade-addons-new\\blade-addons-new\\src\\main\\java\\blade\\addon\\FishModInit.java", "source_location": "L58"}, {"caller_nid": "addon_fishmodinit_fishmodinit_oninitialize", "callee": "init", "is_member_call": false, "source_file": "C:\\blade-addons-new\\blade-addons-new\\src\\main\\java\\blade\\addon\\FishModInit.java", "source_location": "L59"}, {"caller_nid": "addon_fishmodinit_fishmodinit_oninitialize", "callee": "init", "is_member_call": false, "source_file": "C:\\blade-addons-new\\blade-addons-new\\src\\main\\java\\blade\\addon\\FishModInit.java", "source_location": "L60"}, {"caller_nid": "addon_fishmodinit_fishmodinit_oninitialize", "callee": "init", "is_member_call": false, "source_file": "C:\\blade-addons-new\\blade-addons-new\\src\\main\\java\\blade\\addon\\FishModInit.java", "source_location": "L61"}, {"caller_nid": "addon_fishmodinit_fishmodinit_oninitialize", "callee": "init", "is_member_call": false, "source_file": "C:\\blade-addons-new\\blade-addons-new\\src\\main\\java\\blade\\addon\\FishModInit.java", "source_location": "L62"}, {"caller_nid": "addon_fishmodinit_fishmodinit_oninitialize", "callee": "init", "is_member_call": false, "source_file": "C:\\blade-addons-new\\blade-addons-new\\src\\main\\java\\blade\\addon\\FishModInit.java", "source_location": "L63"}, {"caller_nid": "addon_fishmodinit_fishmodinit_oninitialize", "callee": "init", "is_member_call": false, "source_file": "C:\\blade-addons-new\\blade-addons-new\\src\\main\\java\\blade\\addon\\FishModInit.java", "source_location": "L64"}, {"caller_nid": "addon_fishmodinit_fishmodinit_oninitialize", "callee": "register", "is_member_call": false, "source_file": "C:\\blade-addons-new\\blade-addons-new\\src\\main\\java\\blade\\addon\\FishModInit.java", "source_location": "L67"}, {"caller_nid": "addon_fishmodinit_fishmodinit_oninitialize", "callee": "registerLocked", "is_member_call": false, "source_file": "C:\\blade-addons-new\\blade-addons-new\\src\\main\\java\\blade\\addon\\FishModInit.java", "source_location": "L68"}, {"caller_nid": "addon_fishmodinit_fishmodinit_oninitialize", "callee": "getScaledX", "is_member_call": false, "source_file": "C:\\blade-addons-new\\blade-addons-new\\src\\main\\java\\blade\\addon\\FishModInit.java", "source_location": "L69"}, {"caller_nid": "addon_fishmodinit_fishmodinit_oninitialize", "callee": "getScaledY", "is_member_call": false, "source_file": "C:\\blade-addons-new\\blade-addons-new\\src\\main\\java\\blade\\addon\\FishModInit.java", "source_location": "L70"}, {"caller_nid": "addon_fishmodinit_fishmodinit_oninitialize", "callee": "getVisibleRowCount", "is_member_call": false, "source_file": "C:\\blade-addons-new\\blade-addons-new\\src\\main\\java\\blade\\addon\\FishModInit.java", "source_location": "L70"}, {"caller_nid": "addon_fishmodinit_fishmodinit_oninitialize", "callee": "getScaledY", "is_member_call": false, "source_file": "C:\\blade-addons-new\\blade-addons-new\\src\\main\\java\\blade\\addon\\FishModInit.java", "source_location": "L70"}, {"caller_nid": "addon_fishmodinit_fishmodinit_oninitialize", "callee": "register", "is_member_call": false, "source_file": "C:\\blade-addons-new\\blade-addons-new\\src\\main\\java\\blade\\addon\\FishModInit.java", "source_location": "L72"}, {"caller_nid": "addon_fishmodinit_fishmodinit_oninitialize", "callee": "register", "is_member_call": false, "source_file": "C:\\blade-addons-new\\blade-addons-new\\src\\main\\java\\blade\\addon\\FishModInit.java", "source_location": "L73"}, {"caller_nid": "addon_fishmodinit_fishmodinit_oninitialize", "callee": "register", "is_member_call": false, "source_file": "C:\\blade-addons-new\\blade-addons-new\\src\\main\\java\\blade\\addon\\FishModInit.java", "source_location": "L78"}, {"caller_nid": "addon_fishmodinit_fishmodinit_oninitialize", "callee": "register", "is_member_call": false, "source_file": "C:\\blade-addons-new\\blade-addons-new\\src\\main\\java\\blade\\addon\\FishModInit.java", "source_location": "L85"}, {"caller_nid": "addon_fishmodinit_fishmodinit_oninitialize", "callee": "register", "is_member_call": false, "source_file": "C:\\blade-addons-new\\blade-addons-new\\src\\main\\java\\blade\\addon\\FishModInit.java", "source_location": "L86"}, {"caller_nid": "addon_fishmodinit_fishmodinit_oninitialize", "callee": "executes", "is_member_call": false, "source_file": "C:\\blade-addons-new\\blade-addons-new\\src\\main\\java\\blade\\addon\\FishModInit.java", "source_location": "L86"}, {"caller_nid": "addon_fishmodinit_fishmodinit_oninitialize", "callee": "then", "is_member_call": false, "source_file": "C:\\blade-addons-new\\blade-addons-new\\src\\main\\java\\blade\\addon\\FishModInit.java", "source_location": "L86"}, {"caller_nid": "addon_fishmodinit_fishmodinit_oninitialize", "callee": "literal", "is_member_call": false, "source_file": "C:\\blade-addons-new\\blade-addons-new\\src\\main\\java\\blade\\addon\\FishModInit.java", "source_location": "L86"}, {"caller_nid": "addon_fishmodinit_fishmodinit_oninitialize", "callee": "executes", "is_member_call": false, "source_file": "C:\\blade-addons-new\\blade-addons-new\\src\\main\\java\\blade\\addon\\FishModInit.java", "source_location": "L87"}, {"caller_nid": "addon_fishmodinit_fishmodinit_oninitialize", "callee": "argument", "is_member_call": false, "source_file": "C:\\blade-addons-new\\blade-addons-new\\src\\main\\java\\blade\\addon\\FishModInit.java", "source_location": "L87"}, {"caller_nid": "addon_fishmodinit_fishmodinit_oninitialize", "callee": "greedyString", "is_member_call": false, "source_file": "C:\\blade-addons-new\\blade-addons-new\\src\\main\\java\\blade\\addon\\FishModInit.java", "source_location": "L87"}, {"caller_nid": "addon_fishmodinit_fishmodinit_oninitialize", "callee": "trim", "is_member_call": false, "source_file": "C:\\blade-addons-new\\blade-addons-new\\src\\main\\java\\blade\\addon\\FishModInit.java", "source_location": "L89"}, {"caller_nid": "addon_fishmodinit_fishmodinit_oninitialize", "callee": "getString", "is_member_call": false, "source_file": "C:\\blade-addons-new\\blade-addons-new\\src\\main\\java\\blade\\addon\\FishModInit.java", "source_location": "L89"}, {"caller_nid": "addon_fishmodinit_fishmodinit_oninitialize", "callee": "save", "is_member_call": false, "source_file": "C:\\blade-addons-new\\blade-addons-new\\src\\main\\java\\blade\\addon\\FishModInit.java", "source_location": "L91"}, {"caller_nid": "addon_fishmodinit_fishmodinit_oninitialize", "callee": "addChatMessage", "is_member_call": false, "source_file": "C:\\blade-addons-new\\blade-addons-new\\src\\main\\java\\blade\\addon\\FishModInit.java", "source_location": "L92"}, {"caller_nid": "addon_fishmodinit_fishmodinit_oninitialize", "callee": "literal", "is_member_call": false, "source_file": "C:\\blade-addons-new\\blade-addons-new\\src\\main\\java\\blade\\addon\\FishModInit.java", "source_location": "L92"}, {"caller_nid": "addon_fishmodinit_fishmodinit_oninitialize", "callee": "length", "is_member_call": false, "source_file": "C:\\blade-addons-new\\blade-addons-new\\src\\main\\java\\blade\\addon\\FishModInit.java", "source_location": "L92"}, {"caller_nid": "addon_fishmodinit_fishmodinit_oninitialize", "callee": "isEmpty", "is_member_call": false, "source_file": "C:\\blade-addons-new\\blade-addons-new\\src\\main\\java\\blade\\addon\\FishModInit.java", "source_location": "L96"}, {"caller_nid": "addon_fishmodinit_fishmodinit_oninitialize", "callee": "addChatMessage", "is_member_call": false, "source_file": "C:\\blade-addons-new\\blade-addons-new\\src\\main\\java\\blade\\addon\\FishModInit.java", "source_location": "L97"}, {"caller_nid": "addon_fishmodinit_fishmodinit_oninitialize", "callee": "literal", "is_member_call": false, "source_file": "C:\\blade-addons-new\\blade-addons-new\\src\\main\\java\\blade\\addon\\FishModInit.java", "source_location": "L97"}, {"caller_nid": "addon_fishmodinit_fishmodinit_oninitialize", "callee": "length", "is_member_call": false, "source_file": "C:\\blade-addons-new\\blade-addons-new\\src\\main\\java\\blade\\addon\\FishModInit.java", "source_location": "L98"}, {"caller_nid": "addon_fishmodinit_fishmodinit_oninitialize", "callee": "register", "is_member_call": false, "source_file": "C:\\blade-addons-new\\blade-addons-new\\src\\main\\java\\blade\\addon\\FishModInit.java", "source_location": "L103"}, {"caller_nid": "addon_fishmodinit_fishmodinit_oninitialize", "callee": "executes", "is_member_call": false, "source_file": "C:\\blade-addons-new\\blade-addons-new\\src\\main\\java\\blade\\addon\\FishModInit.java", "source_location": "L103"}, {"caller_nid": "addon_fishmodinit_fishmodinit_oninitialize", "callee": "literal", "is_member_call": false, "source_file": "C:\\blade-addons-new\\blade-addons-new\\src\\main\\java\\blade\\addon\\FishModInit.java", "source_location": "L103"}, {"caller_nid": "addon_fishmodinit_fishmodinit_oninitialize", "callee": "send", "is_member_call": false, "source_file": "C:\\blade-addons-new\\blade-addons-new\\src\\main\\java\\blade\\addon\\FishModInit.java", "source_location": "L105"}, {"caller_nid": "addon_fishmodinit_fishmodinit_oninitialize", "callee": "getInstance", "is_member_call": false, "source_file": "C:\\blade-addons-new\\blade-addons-new\\src\\main\\java\\blade\\addon\\FishModInit.java", "source_location": "L105"}, {"caller_nid": "addon_fishmodinit_fishmodinit_oninitialize", "callee": "setScreen", "is_member_call": false, "source_file": "C:\\blade-addons-new\\blade-addons-new\\src\\main\\java\\blade\\addon\\FishModInit.java", "source_location": "L106"}, {"caller_nid": "addon_fishmodinit_fishmodinit_oninitialize", "callee": "getInstance", "is_member_call": false, "source_file": "C:\\blade-addons-new\\blade-addons-new\\src\\main\\java\\blade\\addon\\FishModInit.java", "source_location": "L106"}, {"caller_nid": "addon_fishmodinit_fishmodinit_oninitialize", "callee": "register", "is_member_call": false, "source_file": "C:\\blade-addons-new\\blade-addons-new\\src\\main\\java\\blade\\addon\\FishModInit.java", "source_location": "L110"}, {"caller_nid": "addon_fishmodinit_fishmodinit_oninitialize", "callee": "then", "is_member_call": false, "source_file": "C:\\blade-addons-new\\blade-addons-new\\src\\main\\java\\blade\\addon\\FishModInit.java", "source_location": "L110"}, {"caller_nid": "addon_fishmodinit_fishmodinit_oninitialize", "callee": "executes", "is_member_call": false, "source_file": "C:\\blade-addons-new\\blade-addons-new\\src\\main\\java\\blade\\addon\\FishModInit.java", "source_location": "L110"}, {"caller_nid": "addon_fishmodinit_fishmodinit_oninitialize", "callee": "literal", "is_member_call": false, "source_file": "C:\\blade-addons-new\\blade-addons-new\\src\\main\\java\\blade\\addon\\FishModInit.java", "source_location": "L110"}, {"caller_nid": "addon_fishmodinit_fishmodinit_oninitialize", "callee": "getInstance", "is_member_call": false, "source_file": "C:\\blade-addons-new\\blade-addons-new\\src\\main\\java\\blade\\addon\\FishModInit.java", "source_location": "L112"}, {"caller_nid": "addon_fishmodinit_fishmodinit_oninitialize", "callee": "send", "is_member_call": false, "source_file": "C:\\blade-addons-new\\blade-addons-new\\src\\main\\java\\blade\\addon\\FishModInit.java", "source_location": "L113"}, {"caller_nid": "addon_fishmodinit_fishmodinit_oninitialize", "callee": "setScreen", "is_member_call": false, "source_file": "C:\\blade-addons-new\\blade-addons-new\\src\\main\\java\\blade\\addon\\FishModInit.java", "source_location": "L113"}, {"caller_nid": "addon_fishmodinit_fishmodinit_oninitialize", "callee": "executes", "is_member_call": false, "source_file": "C:\\blade-addons-new\\blade-addons-new\\src\\main\\java\\blade\\addon\\FishModInit.java", "source_location": "L116"}, {"caller_nid": "addon_fishmodinit_fishmodinit_oninitialize", "callee": "argument", "is_member_call": false, "source_file": "C:\\blade-addons-new\\blade-addons-new\\src\\main\\java\\blade\\addon\\FishModInit.java", "source_location": "L116"}, {"caller_nid": "addon_fishmodinit_fishmodinit_oninitialize", "callee": "greedyString", "is_member_call": false, "source_file": "C:\\blade-addons-new\\blade-addons-new\\src\\main\\java\\blade\\addon\\FishModInit.java", "source_location": "L116"}, {"caller_nid": "addon_fishmodinit_fishmodinit_oninitialize", "callee": "getString", "is_member_call": false, "source_file": "C:\\blade-addons-new\\blade-addons-new\\src\\main\\java\\blade\\addon\\FishModInit.java", "source_location": "L118"}, {"caller_nid": "addon_fishmodinit_fishmodinit_oninitialize", "callee": "getInstance", "is_member_call": false, "source_file": "C:\\blade-addons-new\\blade-addons-new\\src\\main\\java\\blade\\addon\\FishModInit.java", "source_location": "L119"}, {"caller_nid": "addon_fishmodinit_fishmodinit_oninitialize", "callee": "send", "is_member_call": false, "source_file": "C:\\blade-addons-new\\blade-addons-new\\src\\main\\java\\blade\\addon\\FishModInit.java", "source_location": "L120"}, {"caller_nid": "addon_fishmodinit_fishmodinit_oninitialize", "callee": "setScreen", "is_member_call": false, "source_file": "C:\\blade-addons-new\\blade-addons-new\\src\\main\\java\\blade\\addon\\FishModInit.java", "source_location": "L120"}, {"caller_nid": "addon_fishmodinit_fishmodinit_oninitialize", "callee": "register", "is_member_call": false, "source_file": "C:\\blade-addons-new\\blade-addons-new\\src\\main\\java\\blade\\addon\\FishModInit.java", "source_location": "L125"}, {"caller_nid": "addon_fishmodinit_fishmodinit_oninitialize", "callee": "executes", "is_member_call": false, "source_file": "C:\\blade-addons-new\\blade-addons-new\\src\\main\\java\\blade\\addon\\FishModInit.java", "source_location": "L125"}, {"caller_nid": "addon_fishmodinit_fishmodinit_oninitialize", "callee": "literal", "is_member_call": false, "source_file": "C:\\blade-addons-new\\blade-addons-new\\src\\main\\java\\blade\\addon\\FishModInit.java", "source_location": "L125"}, {"caller_nid": "addon_fishmodinit_fishmodinit_oninitialize", "callee": "getInstance", "is_member_call": false, "source_file": "C:\\blade-addons-new\\blade-addons-new\\src\\main\\java\\blade\\addon\\FishModInit.java", "source_location": "L126"}, {"caller_nid": "addon_fishmodinit_fishmodinit_oninitialize", "callee": "send", "is_member_call": false, "source_file": "C:\\blade-addons-new\\blade-addons-new\\src\\main\\java\\blade\\addon\\FishModInit.java", "source_location": "L127"}, {"caller_nid": "addon_fishmodinit_fishmodinit_oninitialize", "callee": "addChatMessage", "is_member_call": false, "source_file": "C:\\blade-addons-new\\blade-addons-new\\src\\main\\java\\blade\\addon\\FishModInit.java", "source_location": "L128"}, {"caller_nid": "addon_fishmodinit_fishmodinit_oninitialize", "callee": "literal", "is_member_call": false, "source_file": "C:\\blade-addons-new\\blade-addons-new\\src\\main\\java\\blade\\addon\\FishModInit.java", "source_location": "L128"}, {"caller_nid": "addon_fishmodinit_fishmodinit_oninitialize", "callee": "addChatMessage", "is_member_call": false, "source_file": "C:\\blade-addons-new\\blade-addons-new\\src\\main\\java\\blade\\addon\\FishModInit.java", "source_location": "L129"}, {"caller_nid": "addon_fishmodinit_fishmodinit_oninitialize", "callee": "literal", "is_member_call": false, "source_file": "C:\\blade-addons-new\\blade-addons-new\\src\\main\\java\\blade\\addon\\FishModInit.java", "source_location": "L129"}, {"caller_nid": "addon_fishmodinit_fishmodinit_oninitialize", "callee": "getCurrentLocation", "is_member_call": false, "source_file": "C:\\blade-addons-new\\blade-addons-new\\src\\main\\java\\blade\\addon\\FishModInit.java", "source_location": "L129"}, {"caller_nid": "addon_fishmodinit_fishmodinit_oninitialize", "callee": "addChatMessage", "is_member_call": false, "source_file": "C:\\blade-addons-new\\blade-addons-new\\src\\main\\java\\blade\\addon\\FishModInit.java", "source_location": "L130"}, {"caller_nid": "addon_fishmodinit_fishmodinit_oninitialize", "callee": "literal", "is_member_call": false, "source_file": "C:\\blade-addons-new\\blade-addons-new\\src\\main\\java\\blade\\addon\\FishModInit.java", "source_location": "L130"}, {"caller_nid": "addon_fishmodinit_fishmodinit_oninitialize", "callee": "inSkyblock", "is_member_call": false, "source_file": "C:\\blade-addons-new\\blade-addons-new\\src\\main\\java\\blade\\addon\\FishModInit.java", "source_location": "L130"}, {"caller_nid": "addon_fishmodinit_fishmodinit_oninitialize", "callee": "addChatMessage", "is_member_call": false, "source_file": "C:\\blade-addons-new\\blade-addons-new\\src\\main\\java\\blade\\addon\\FishModInit.java", "source_location": "L131"}, {"caller_nid": "addon_fishmodinit_fishmodinit_oninitialize", "callee": "literal", "is_member_call": false, "source_file": "C:\\blade-addons-new\\blade-addons-new\\src\\main\\java\\blade\\addon\\FishModInit.java", "source_location": "L131"}, {"caller_nid": "addon_fishmodinit_fishmodinit_oninitialize", "callee": "inDungeon", "is_member_call": false, "source_file": "C:\\blade-addons-new\\blade-addons-new\\src\\main\\java\\blade\\addon\\FishModInit.java", "source_location": "L131"}, {"caller_nid": "addon_fishmodinit_fishmodinit_oninitialize", "callee": "addChatMessage", "is_member_call": false, "source_file": "C:\\blade-addons-new\\blade-addons-new\\src\\main\\java\\blade\\addon\\FishModInit.java", "source_location": "L132"}, {"caller_nid": "addon_fishmodinit_fishmodinit_oninitialize", "callee": "literal", "is_member_call": false, "source_file": "C:\\blade-addons-new\\blade-addons-new\\src\\main\\java\\blade\\addon\\FishModInit.java", "source_location": "L132"}, {"caller_nid": "addon_fishmodinit_fishmodinit_oninitialize", "callee": "addChatMessage", "is_member_call": false, "source_file": "C:\\blade-addons-new\\blade-addons-new\\src\\main\\java\\blade\\addon\\FishModInit.java", "source_location": "L133"}, {"caller_nid": "addon_fishmodinit_fishmodinit_oninitialize", "callee": "literal", "is_member_call": false, "source_file": "C:\\blade-addons-new\\blade-addons-new\\src\\main\\java\\blade\\addon\\FishModInit.java", "source_location": "L133"}, {"caller_nid": "addon_fishmodinit_fishmodinit_oninitialize", "callee": "size", "is_member_call": false, "source_file": "C:\\blade-addons-new\\blade-addons-new\\src\\main\\java\\blade\\addon\\FishModInit.java", "source_location": "L133"}, {"caller_nid": "addon_fishmodinit_fishmodinit_oninitialize", "callee": "getPuzzles", "is_member_call": false, "source_file": "C:\\blade-addons-new\\blade-addons-new\\src\\main\\java\\blade\\addon\\FishModInit.java", "source_location": "L133"}, {"caller_nid": "addon_fishmodinit_fishmodinit_oninitialize", "callee": "getPuzzles", "is_member_call": false, "source_file": "C:\\blade-addons-new\\blade-addons-new\\src\\main\\java\\blade\\addon\\FishModInit.java", "source_location": "L133"}, {"caller_nid": "addon_fishmodinit_fishmodinit_oninitialize", "callee": "addChatMessage", "is_member_call": false, "source_file": "C:\\blade-addons-new\\blade-addons-new\\src\\main\\java\\blade\\addon\\FishModInit.java", "source_location": "L134"}, {"caller_nid": "addon_fishmodinit_fishmodinit_oninitialize", "callee": "literal", "is_member_call": false, "source_file": "C:\\blade-addons-new\\blade-addons-new\\src\\main\\java\\blade\\addon\\FishModInit.java", "source_location": "L134"}, {"caller_nid": "addon_fishmodinit_fishmodinit_oninitialize", "callee": "runStarted", "is_member_call": false, "source_file": "C:\\blade-addons-new\\blade-addons-new\\src\\main\\java\\blade\\addon\\FishModInit.java", "source_location": "L134"}, {"caller_nid": "addon_fishmodinit_fishmodinit_oninitialize", "callee": "addChatMessage", "is_member_call": false, "source_file": "C:\\blade-addons-new\\blade-addons-new\\src\\main\\java\\blade\\addon\\FishModInit.java", "source_location": "L134"}, {"caller_nid": "addon_fishmodinit_fishmodinit_oninitialize", "callee": "literal", "is_member_call": false, "source_file": "C:\\blade-addons-new\\blade-addons-new\\src\\main\\java\\blade\\addon\\FishModInit.java", "source_location": "L134"}, {"caller_nid": "addon_fishmodinit_fishmodinit_oninitialize", "callee": "getMessage", "is_member_call": false, "source_file": "C:\\blade-addons-new\\blade-addons-new\\src\\main\\java\\blade\\addon\\FishModInit.java", "source_location": "L134"}, {"caller_nid": "addon_fishmodinit_fishmodinit_oninitialize", "callee": "addChatMessage", "is_member_call": false, "source_file": "C:\\blade-addons-new\\blade-addons-new\\src\\main\\java\\blade\\addon\\FishModInit.java", "source_location": "L135"}, {"caller_nid": "addon_fishmodinit_fishmodinit_oninitialize", "callee": "literal", "is_member_call": false, "source_file": "C:\\blade-addons-new\\blade-addons-new\\src\\main\\java\\blade\\addon\\FishModInit.java", "source_location": "L135"}, {"caller_nid": "addon_fishmodinit_fishmodinit_oninitialize", "callee": "addChatMessage", "is_member_call": false, "source_file": "C:\\blade-addons-new\\blade-addons-new\\src\\main\\java\\blade\\addon\\FishModInit.java", "source_location": "L135"}, {"caller_nid": "addon_fishmodinit_fishmodinit_oninitialize", "callee": "literal", "is_member_call": false, "source_file": "C:\\blade-addons-new\\blade-addons-new\\src\\main\\java\\blade\\addon\\FishModInit.java", "source_location": "L135"}, {"caller_nid": "addon_fishmodinit_fishmodinit_oninitialize", "callee": "getMessage", "is_member_call": false, "source_file": "C:\\blade-addons-new\\blade-addons-new\\src\\main\\java\\blade\\addon\\FishModInit.java", "source_location": "L135"}, {"caller_nid": "addon_fishmodinit_fishmodinit_oninitialize", "callee": "addChatMessage", "is_member_call": false, "source_file": "C:\\blade-addons-new\\blade-addons-new\\src\\main\\java\\blade\\addon\\FishModInit.java", "source_location": "L136"}, {"caller_nid": "addon_fishmodinit_fishmodinit_oninitialize", "callee": "literal", "is_member_call": false, "source_file": "C:\\blade-addons-new\\blade-addons-new\\src\\main\\java\\blade\\addon\\FishModInit.java", "source_location": "L136"}, {"caller_nid": "addon_fishmodinit_fishmodinit_oninitialize", "callee": "isModLoaded", "is_member_call": false, "source_file": "C:\\blade-addons-new\\blade-addons-new\\src\\main\\java\\blade\\addon\\FishModInit.java", "source_location": "L136"}, {"caller_nid": "addon_fishmodinit_fishmodinit_oninitialize", "callee": "getInstance", "is_member_call": false, "source_file": "C:\\blade-addons-new\\blade-addons-new\\src\\main\\java\\blade\\addon\\FishModInit.java", "source_location": "L136"}, {"caller_nid": "addon_fishmodinit_fishmodinit_oninitialize", "callee": "addChatMessage", "is_member_call": false, "source_file": "C:\\blade-addons-new\\blade-addons-new\\src\\main\\java\\blade\\addon\\FishModInit.java", "source_location": "L136"}, {"caller_nid": "addon_fishmodinit_fishmodinit_oninitialize", "callee": "literal", "is_member_call": false, "source_file": "C:\\blade-addons-new\\blade-addons-new\\src\\main\\java\\blade\\addon\\FishModInit.java", "source_location": "L136"}, {"caller_nid": "addon_fishmodinit_fishmodinit_oninitialize", "callee": "getNetworkHandler", "is_member_call": false, "source_file": "C:\\blade-addons-new\\blade-addons-new\\src\\main\\java\\blade\\addon\\FishModInit.java", "source_location": "L138"}, {"caller_nid": "addon_fishmodinit_fishmodinit_oninitialize", "callee": "addChatMessage", "is_member_call": false, "source_file": "C:\\blade-addons-new\\blade-addons-new\\src\\main\\java\\blade\\addon\\FishModInit.java", "source_location": "L140"}, {"caller_nid": "addon_fishmodinit_fishmodinit_oninitialize", "callee": "literal", "is_member_call": false, "source_file": "C:\\blade-addons-new\\blade-addons-new\\src\\main\\java\\blade\\addon\\FishModInit.java", "source_location": "L140"}, {"caller_nid": "addon_fishmodinit_fishmodinit_oninitialize", "callee": "getPlayerList", "is_member_call": false, "source_file": "C:\\blade-addons-new\\blade-addons-new\\src\\main\\java\\blade\\addon\\FishModInit.java", "source_location": "L143"}, {"caller_nid": "addon_fishmodinit_fishmodinit_oninitialize", "callee": "getDisplayName", "is_member_call": false, "source_file": "C:\\blade-addons-new\\blade-addons-new\\src\\main\\java\\blade\\addon\\FishModInit.java", "source_location": "L145"}, {"caller_nid": "addon_fishmodinit_fishmodinit_oninitialize", "callee": "getString", "is_member_call": false, "source_file": "C:\\blade-addons-new\\blade-addons-new\\src\\main\\java\\blade\\addon\\FishModInit.java", "source_location": "L146"}, {"caller_nid": "addon_fishmodinit_fishmodinit_oninitialize", "callee": "getDisplayName", "is_member_call": false, "source_file": "C:\\blade-addons-new\\blade-addons-new\\src\\main\\java\\blade\\addon\\FishModInit.java", "source_location": "L146"}, {"caller_nid": "addon_fishmodinit_fishmodinit_oninitialize", "callee": "trim", "is_member_call": false, "source_file": "C:\\blade-addons-new\\blade-addons-new\\src\\main\\java\\blade\\addon\\FishModInit.java", "source_location": "L147"}, {"caller_nid": "addon_fishmodinit_fishmodinit_oninitialize", "callee": "replaceAll", "is_member_call": false, "source_file": "C:\\blade-addons-new\\blade-addons-new\\src\\main\\java\\blade\\addon\\FishModInit.java", "source_location": "L147"}, {"caller_nid": "addon_fishmodinit_fishmodinit_oninitialize", "callee": "isEmpty", "is_member_call": false, "source_file": "C:\\blade-addons-new\\blade-addons-new\\src\\main\\java\\blade\\addon\\FishModInit.java", "source_location": "L148"}, {"caller_nid": "addon_fishmodinit_fishmodinit_oninitialize", "callee": "addChatMessage", "is_member_call": false, "source_file": "C:\\blade-addons-new\\blade-addons-new\\src\\main\\java\\blade\\addon\\FishModInit.java", "source_location": "L149"}, {"caller_nid": "addon_fishmodinit_fishmodinit_oninitialize", "callee": "literal", "is_member_call": false, "source_file": "C:\\blade-addons-new\\blade-addons-new\\src\\main\\java\\blade\\addon\\FishModInit.java", "source_location": "L149"}, {"caller_nid": "addon_fishmodinit_fishmodinit_oninitialize", "callee": "addChatMessage", "is_member_call": false, "source_file": "C:\\blade-addons-new\\blade-addons-new\\src\\main\\java\\blade\\addon\\FishModInit.java", "source_location": "L151"}, {"caller_nid": "addon_fishmodinit_fishmodinit_oninitialize", "callee": "literal", "is_member_call": false, "source_file": "C:\\blade-addons-new\\blade-addons-new\\src\\main\\java\\blade\\addon\\FishModInit.java", "source_location": "L151"}, {"caller_nid": "addon_fishmodinit_fishmodinit_oninitialize", "callee": "getScoreboard", "is_member_call": false, "source_file": "C:\\blade-addons-new\\blade-addons-new\\src\\main\\java\\blade\\addon\\FishModInit.java", "source_location": "L155"}, {"caller_nid": "addon_fishmodinit_fishmodinit_oninitialize", "callee": "getObjectiveForSlot", "is_member_call": false, "source_file": "C:\\blade-addons-new\\blade-addons-new\\src\\main\\java\\blade\\addon\\FishModInit.java", "source_location": "L156"}, {"caller_nid": "addon_fishmodinit_fishmodinit_oninitialize", "callee": "addChatMessage", "is_member_call": false, "source_file": "C:\\blade-addons-new\\blade-addons-new\\src\\main\\java\\blade\\addon\\FishModInit.java", "source_location": "L158"}, {"caller_nid": "addon_fishmodinit_fishmodinit_oninitialize", "callee": "literal", "is_member_call": false, "source_file": "C:\\blade-addons-new\\blade-addons-new\\src\\main\\java\\blade\\addon\\FishModInit.java", "source_location": "L158"}, {"caller_nid": "addon_fishmodinit_fishmodinit_oninitialize", "callee": "addChatMessage", "is_member_call": false, "source_file": "C:\\blade-addons-new\\blade-addons-new\\src\\main\\java\\blade\\addon\\FishModInit.java", "source_location": "L160"}, {"caller_nid": "addon_fishmodinit_fishmodinit_oninitialize", "callee": "literal", "is_member_call": false, "source_file": "C:\\blade-addons-new\\blade-addons-new\\src\\main\\java\\blade\\addon\\FishModInit.java", "source_location": "L160"}, {"caller_nid": "addon_fishmodinit_fishmodinit_oninitialize", "callee": "getString", "is_member_call": false, "source_file": "C:\\blade-addons-new\\blade-addons-new\\src\\main\\java\\blade\\addon\\FishModInit.java", "source_location": "L160"}, {"caller_nid": "addon_fishmodinit_fishmodinit_oninitialize", "callee": "getDisplayName", "is_member_call": false, "source_file": "C:\\blade-addons-new\\blade-addons-new\\src\\main\\java\\blade\\addon\\FishModInit.java", "source_location": "L160"}, {"caller_nid": "addon_fishmodinit_fishmodinit_oninitialize", "callee": "getScoreboardEntries", "is_member_call": false, "source_file": "C:\\blade-addons-new\\blade-addons-new\\src\\main\\java\\blade\\addon\\FishModInit.java", "source_location": "L161"}, {"caller_nid": "addon_fishmodinit_fishmodinit_oninitialize", "callee": "owner", "is_member_call": false, "source_file": "C:\\blade-addons-new\\blade-addons-new\\src\\main\\java\\blade\\addon\\FishModInit.java", "source_location": "L162"}, {"caller_nid": "addon_fishmodinit_fishmodinit_oninitialize", "callee": "getScoreHolderTeam", "is_member_call": false, "source_file": "C:\\blade-addons-new\\blade-addons-new\\src\\main\\java\\blade\\addon\\FishModInit.java", "source_location": "L163"}, {"caller_nid": "addon_fishmodinit_fishmodinit_oninitialize", "callee": "getString", "is_member_call": false, "source_file": "C:\\blade-addons-new\\blade-addons-new\\src\\main\\java\\blade\\addon\\FishModInit.java", "source_location": "L165"}, {"caller_nid": "addon_fishmodinit_fishmodinit_oninitialize", "callee": "getPrefix", "is_member_call": false, "source_file": "C:\\blade-addons-new\\blade-addons-new\\src\\main\\java\\blade\\addon\\FishModInit.java", "source_location": "L165"}, {"caller_nid": "addon_fishmodinit_fishmodinit_oninitialize", "callee": "getString", "is_member_call": false, "source_file": "C:\\blade-addons-new\\blade-addons-new\\src\\main\\java\\blade\\addon\\FishModInit.java", "source_location": "L165"}, {"caller_nid": "addon_fishmodinit_fishmodinit_oninitialize", "callee": "getSuffix", "is_member_call": false, "source_file": "C:\\blade-addons-new\\blade-addons-new\\src\\main\\java\\blade\\addon\\FishModInit.java", "source_location": "L165"}, {"caller_nid": "addon_fishmodinit_fishmodinit_oninitialize", "callee": "getString", "is_member_call": false, "source_file": "C:\\blade-addons-new\\blade-addons-new\\src\\main\\java\\blade\\addon\\FishModInit.java", "source_location": "L166"}, {"caller_nid": "addon_fishmodinit_fishmodinit_oninitialize", "callee": "name", "is_member_call": false, "source_file": "C:\\blade-addons-new\\blade-addons-new\\src\\main\\java\\blade\\addon\\FishModInit.java", "source_location": "L166"}, {"caller_nid": "addon_fishmodinit_fishmodinit_oninitialize", "callee": "trim", "is_member_call": false, "source_file": "C:\\blade-addons-new\\blade-addons-new\\src\\main\\java\\blade\\addon\\FishModInit.java", "source_location": "L167"}, {"caller_nid": "addon_fishmodinit_fishmodinit_oninitialize", "callee": "replaceAll", "is_member_call": false, "source_file": "C:\\blade-addons-new\\blade-addons-new\\src\\main\\java\\blade\\addon\\FishModInit.java", "source_location": "L167"}, {"caller_nid": "addon_fishmodinit_fishmodinit_oninitialize", "callee": "isEmpty", "is_member_call": false, "source_file": "C:\\blade-addons-new\\blade-addons-new\\src\\main\\java\\blade\\addon\\FishModInit.java", "source_location": "L168"}, {"caller_nid": "addon_fishmodinit_fishmodinit_oninitialize", "callee": "addChatMessage", "is_member_call": false, "source_file": "C:\\blade-addons-new\\blade-addons-new\\src\\main\\java\\blade\\addon\\FishModInit.java", "source_location": "L169"}, {"caller_nid": "addon_fishmodinit_fishmodinit_oninitialize", "callee": "literal", "is_member_call": false, "source_file": "C:\\blade-addons-new\\blade-addons-new\\src\\main\\java\\blade\\addon\\FishModInit.java", "source_location": "L169"}, {"caller_nid": "addon_fishmodinit_fishmodinit_oninitialize", "callee": "addChatMessage", "is_member_call": false, "source_file": "C:\\blade-addons-new\\blade-addons-new\\src\\main\\java\\blade\\addon\\FishModInit.java", "source_location": "L173"}, {"caller_nid": "addon_fishmodinit_fishmodinit_oninitialize", "callee": "literal", "is_member_call": false, "source_file": "C:\\blade-addons-new\\blade-addons-new\\src\\main\\java\\blade\\addon\\FishModInit.java", "source_location": "L173"}, {"caller_nid": "addon_fishmodinit_fishmodinit_oninitialize", "callee": "register", "is_member_call": false, "source_file": "C:\\blade-addons-new\\blade-addons-new\\src\\main\\java\\blade\\addon\\FishModInit.java", "source_location": "L181"}, {"caller_nid": "addon_fishmodinit_fishmodinit_oninitialize", "callee": "renderHud", "is_member_call": false, "source_file": "C:\\blade-addons-new\\blade-addons-new\\src\\main\\java\\blade\\addon\\FishModInit.java", "source_location": "L181"}, {"caller_nid": "addon_fishmodinit_fishmodinit_oninitialize", "callee": "register", "is_member_call": false, "source_file": "C:\\blade-addons-new\\blade-addons-new\\src\\main\\java\\blade\\addon\\FishModInit.java", "source_location": "L182"}, {"caller_nid": "addon_fishmodinit_fishmodinit_oninitialize", "callee": "renderHud", "is_member_call": false, "source_file": "C:\\blade-addons-new\\blade-addons-new\\src\\main\\java\\blade\\addon\\FishModInit.java", "source_location": "L182"}, {"caller_nid": "addon_fishmodinit_fishmodinit_oninitialize", "callee": "register", "is_member_call": false, "source_file": "C:\\blade-addons-new\\blade-addons-new\\src\\main\\java\\blade\\addon\\FishModInit.java", "source_location": "L183"}, {"caller_nid": "addon_fishmodinit_fishmodinit_oninitialize", "callee": "renderHud", "is_member_call": false, "source_file": "C:\\blade-addons-new\\blade-addons-new\\src\\main\\java\\blade\\addon\\FishModInit.java", "source_location": "L183"}, {"caller_nid": "addon_fishmodinit_fishmodinit_oninitialize", "callee": "register", "is_member_call": false, "source_file": "C:\\blade-addons-new\\blade-addons-new\\src\\main\\java\\blade\\addon\\FishModInit.java", "source_location": "L184"}, {"caller_nid": "addon_fishmodinit_fishmodinit_oninitialize", "callee": "renderHud", "is_member_call": false, "source_file": "C:\\blade-addons-new\\blade-addons-new\\src\\main\\java\\blade\\addon\\FishModInit.java", "source_location": "L184"}, {"caller_nid": "addon_fishmodinit_fishmodinit_oninitialize", "callee": "register", "is_member_call": false, "source_file": "C:\\blade-addons-new\\blade-addons-new\\src\\main\\java\\blade\\addon\\FishModInit.java", "source_location": "L185"}, {"caller_nid": "addon_fishmodinit_fishmodinit_oninitialize", "callee": "renderHud", "is_member_call": false, "source_file": "C:\\blade-addons-new\\blade-addons-new\\src\\main\\java\\blade\\addon\\FishModInit.java", "source_location": "L185"}, {"caller_nid": "addon_fishmodinit_fishmodinit_oninitialize", "callee": "isModLoaded", "is_member_call": false, "source_file": "C:\\blade-addons-new\\blade-addons-new\\src\\main\\java\\blade\\addon\\FishModInit.java", "source_location": "L187"}, {"caller_nid": "addon_fishmodinit_fishmodinit_oninitialize", "callee": "getInstance", "is_member_call": false, "source_file": "C:\\blade-addons-new\\blade-addons-new\\src\\main\\java\\blade\\addon\\FishModInit.java", "source_location": "L187"}, {"caller_nid": "addon_fishmodinit_fishmodinit_oninitialize", "callee": "init", "is_member_call": false, "source_file": "C:\\blade-addons-new\\blade-addons-new\\src\\main\\java\\blade\\addon\\FishModInit.java", "source_location": "L189"}, {"caller_nid": "addon_fishmodinit_fishmodinit_oninitialize", "callee": "init", "is_member_call": false, "source_file": "C:\\blade-addons-new\\blade-addons-new\\src\\main\\java\\blade\\addon\\FishModInit.java", "source_location": "L190"}, {"caller_nid": "addon_fishmodinit_fishmodinit_oninitialize", "callee": "load", "is_member_call": false, "source_file": "C:\\blade-addons-new\\blade-addons-new\\src\\main\\java\\blade\\addon\\FishModInit.java", "source_location": "L191"}, {"caller_nid": "addon_fishmodinit_fishmodinit_oninitialize", "callee": "init", "is_member_call": false, "source_file": "C:\\blade-addons-new\\blade-addons-new\\src\\main\\java\\blade\\addon\\FishModInit.java", "source_location": "L192"}, {"caller_nid": "addon_fishmodinit_fishmodinit_oninitialize", "callee": "init", "is_member_call": false, "source_file": "C:\\blade-addons-new\\blade-addons-new\\src\\main\\java\\blade\\addon\\FishModInit.java", "source_location": "L193"}, {"caller_nid": "addon_fishmodinit_fishmodinit_oninitialize", "callee": "init", "is_member_call": false, "source_file": "C:\\blade-addons-new\\blade-addons-new\\src\\main\\java\\blade\\addon\\FishModInit.java", "source_location": "L194"}, {"caller_nid": "addon_fishmodinit_fishmodinit_oninitialize", "callee": "init", "is_member_call": false, "source_file": "C:\\blade-addons-new\\blade-addons-new\\src\\main\\java\\blade\\addon\\FishModInit.java", "source_location": "L195"}, {"caller_nid": "addon_fishmodinit_fishmodinit_oninitialize", "callee": "init", "is_member_call": false, "source_file": "C:\\blade-addons-new\\blade-addons-new\\src\\main\\java\\blade\\addon\\FishModInit.java", "source_location": "L196"}, {"caller_nid": "addon_fishmodinit_fishmodinit_oninitialize", "callee": "init", "is_member_call": false, "source_file": "C:\\blade-addons-new\\blade-addons-new\\src\\main\\java\\blade\\addon\\FishModInit.java", "source_location": "L197"}, {"caller_nid": "addon_fishmodinit_fishmodinit_oninitialize", "callee": "init", "is_member_call": false, "source_file": "C:\\blade-addons-new\\blade-addons-new\\src\\main\\java\\blade\\addon\\FishModInit.java", "source_location": "L198"}, {"caller_nid": "addon_fishmodinit_fishmodinit_oninitialize", "callee": "init", "is_member_call": false, "source_file": "C:\\blade-addons-new\\blade-addons-new\\src\\main\\java\\blade\\addon\\FishModInit.java", "source_location": "L199"}, {"caller_nid": "addon_fishmodinit_fishmodinit_oninitialize", "callee": "init", "is_member_call": false, "source_file": "C:\\blade-addons-new\\blade-addons-new\\src\\main\\java\\blade\\addon\\FishModInit.java", "source_location": "L200"}, {"caller_nid": "addon_fishmodinit_fishmodinit_oninitialize", "callee": "init", "is_member_call": false, "source_file": "C:\\blade-addons-new\\blade-addons-new\\src\\main\\java\\blade\\addon\\FishModInit.java", "source_location": "L201"}]}